<?xml version="1.0" encoding="utf-8"?><Report layerType="OldCompatible" version="2"><cp dn="2" dt="4" dcd="18.09.2016 7:52:37" l="1" /><dp page_count="000006" det_add_col="false" det_show_nds="true" det_add_accums="false" det_add_limit="false" det_add_GMT="true" det_add_max_lim="false" det_add_rule="false" /><b sd="03.09.2016" ed="17.09.2016" /><ds n="79139312288" sim="89701015538957838815" pt="Сетевой ресурс" t="30,0849" f="35,5000" cn="руб." sd="03.09.2016" ed="17.09.2016"><i d="03.09.2016 12:38:11" n="internet.mts.ru" zp="" zv="" s="LTE (4G)" a="" du="244Kb" c="0" dup="300Kb" f="0" bd="03.09.2016 12:46:23" cur="810" gmt="+07:00" /><i d="03.09.2016 13:00:03" n="&lt;--79831245623" zp="" zv="" s="Телеф. (3G)" a="" du="1:14" c="0" dup="1:14" f="0" bd="03.09.2016 13:03:55" cur="810" gmt="+07:00" /><i d="03.09.2016 13:20:43" n="&lt;--79139112855" zp="" zv="" s="Телеф. (3G)" a="" du="11:02" c="0" dup="11:02" f="0" bd="03.09.2016 13:33:54" cur="810" gmt="+07:00" /><i d="03.09.2016 16:39:25" n="79831245623" zp="" zv="" s="Телеф." a="" du="6:25" c="0" dup="7:00" f="0" bd="03.09.2016 16:45:50" cur="810" gmt="+07:00" /><i d="03.09.2016 17:09:16" n="&lt;--79831245623" zp="" zv="" s="Телеф. (3G)" a="" du="0:21" c="0" dup="0:21" f="0" bd="03.09.2016 17:13:49" cur="810" gmt="+07:00" /><i d="03.09.2016 17:40:08" n="internet.mts.ru" zp="" zv="" s="HSDPA (3G)" a="" du="48Kb" c="0" dup="100Kb" f="0" bd="03.09.2016 17:48:23" cur="810" gmt="+07:00" /><i d="03.09.2016 19:36:30" n="internet.mts.ru" zp="" zv="" s="LTE (4G)" a="" du="35Kb" c="0" dup="100Kb" f="0" bd="03.09.2016 19:44:11" cur="810" gmt="+07:00" /><i d="03.09.2016 19:51:10" n="&lt;--79059341322" zp="" zv="" s="Телеф. (3G)" a="" du="3:20" c="0" dup="3:20" f="0" bd="03.09.2016 19:58:53" cur="810" gmt="+07:00" /><i d="04.09.2016 12:21:12" n="&lt;--79831245623" zp="" zv="" s="Телеф. (3G)" a="" du="7:23" c="0" dup="7:23" f="0" bd="04.09.2016 12:33:45" cur="810" gmt="+07:00" /><i d="04.09.2016 12:30:52" n="79139112855" zp="" zv="" s="Телеф." a="" du="6:07" c="0" dup="7:00" f="0" bd="04.09.2016 12:36:59" cur="810" gmt="+07:00" /><i d="04.09.2016 12:43:43" n="&lt;--79139112855" zp="" zv="" s="Телеф. (3G)" a="" du="0:17" c="0" dup="0:17" f="0" bd="04.09.2016 12:48:53" cur="810" gmt="+07:00" /><i d="04.09.2016 13:49:34" n="&lt;--79831245623" zp="" zv="" s="Телеф." a="" du="0:30" c="0" dup="0:30" f="0" bd="04.09.2016 13:53:54" cur="810" gmt="+07:00" /><i d="04.09.2016 13:53:19" n="79831245623" zp="" zv="" s="Телеф." a="" du="0:32" c="0" dup="1:00" f="0" bd="04.09.2016 13:53:51" cur="810" gmt="+07:00" /><i d="04.09.2016 14:11:50" n="internet.mts.ru" zp="" zv="" s="LTE (4G)" a="" du="50Kb" c="0" dup="100Kb" f="0" bd="04.09.2016 14:19:25" cur="810" gmt="+07:00" /><i d="04.09.2016 14:12:19" n="900" zp="" zv="" s="sms o" a="" du="1" c="0,8475" dup="1" f="1,0000" bd="04.09.2016 14:12:20" cur="810" gmt="+07:00" /><i d="04.09.2016 14:12:23" n="&lt;--sms:900" zp="" zv="" s="sms i" a="" du="0" c="0" dup="1" f="0" bd="04.09.2016 14:14:14" cur="810" gmt="+07:00" /><i d="04.09.2016 14:12:24" n="&lt;--sms:900" zp="" zv="" s="sms i" a="" du="0" c="0" dup="1" f="0" bd="04.09.2016 14:14:14" cur="810" gmt="+07:00" /><i d="04.09.2016 14:13:38" n="&lt;--sms:MTC" zp="" zv="" s="sms i" a="" du="0" c="0" dup="1" f="0" bd="04.09.2016 14:18:56" cur="810" gmt="+07:00" /><i d="04.09.2016 15:11:50" n="internet.mts.ru" zp="" zv="" s="LTE (4G)" a="" du="1Kb" c="0" dup="100Kb" f="0" bd="04.09.2016 15:20:22" cur="810" gmt="+07:00" /><i d="04.09.2016 15:55:45" n="79139112855" zp="" zv="" s="Телеф." a="" du="0:14" c="0" dup="1:00" f="0" bd="04.09.2016 15:55:59" cur="810" gmt="+07:00" /><i d="04.09.2016 16:02:51" n="&lt;--79137637210" zp="" zv="" s="Телеф. (3G)" a="" du="24:30" c="0" g="b" dup="24:30" f="0" bd="04.09.2016 16:28:34" cur="810" gmt="+07:00" /><i d="04.09.2016 16:11:50" n="internet.mts.ru" zp="" zv="" s="LTE (4G)" a="" du="2326Kb" c="0" g="e" dup="2400Kb" f="0" bd="04.09.2016 16:20:26" cur="810" gmt="+07:00" /><i d="04.09.2016 16:35:45" n="&lt;--sms:900" zp="" zv="" s="sms i" a="" du="0" c="0" dup="1" f="0" bd="04.09.2016 16:38:43" cur="810" gmt="+07:00" /><i d="04.09.2016 16:35:46" n="&lt;--sms:900" zp="" zv="" s="sms i" a="" du="0" c="0" dup="1" f="0" bd="04.09.2016 16:38:43" cur="810" gmt="+07:00" /><i d="04.09.2016 16:41:18" n="internet.mts.ru" zp="" zv="" s="LTE (4G)" a="" du="19077Kb" c="0" dup="19100Kb" f="0" bd="04.09.2016 16:50:14" cur="810" gmt="+07:00" /><i d="04.09.2016 17:11:50" n="internet.mts.ru" zp="" zv="" s="HSDPA (3G)" a="" du="29Kb" c="0" dup="100Kb" f="0" bd="04.09.2016 17:20:12" cur="810" gmt="+07:00" /><i d="04.09.2016 20:29:56" n="79831245623" zp="" zv="" s="Телеф." a="" du="6:17" c="0" dup="7:00" f="0" bd="04.09.2016 20:36:13" cur="810" gmt="+07:00" /><i d="04.09.2016 21:02:09" n="Traffic_Category_900_033.001_G" zp="" zv="" s="HSDPA (3G)" a="" du="1Kb" c="0" dup="1Kb" f="0" bd="04.09.2016 21:11:09" cur="810" gmt="+07:00" /><i d="05.09.2016 8:39:41" n="internet.mts.ru" zp="" zv="" s="gprs" a="" du="98Kb" c="0" dup="100Kb" f="0" bd="05.09.2016 8:46:13" cur="810" gmt="+07:00" /><i d="05.09.2016 8:51:31" n="79831245623" zp="" zv="" s="Телеф." a="" du="3:55" c="0" dup="4:00" f="0" bd="05.09.2016 8:55:26" cur="810" gmt="+07:00" /><i d="05.09.2016 9:25:28" n="internet.mts.ru" zp="" zv="" s="LTE (4G)" a="" du="94Kb" c="0" dup="100Kb" f="0" bd="05.09.2016 9:32:19" cur="810" gmt="+07:00" /><i d="05.09.2016 11:52:26" n="3159999" zp="" zv="" s="Телеф." a="" du="3:04" c="5,0847" dup="4:00" f="6,0000" bd="05.09.2016 11:55:30" cur="810" gmt="+07:00" /><i d="05.09.2016 13:38:56" n="79139112855" zp="" zv="" s="Телеф." a="" du="0:23" c="0" dup="1:00" f="0" bd="05.09.2016 13:39:19" cur="810" gmt="+07:00" /><i d="05.09.2016 15:06:24" n="&lt;--sms:900" zp="" zv="" s="sms i" a="" du="0" c="0" dup="1" f="0" bd="05.09.2016 15:09:45" cur="810" gmt="+07:00" /><i d="05.09.2016 15:30:29" n="2276227" zp="" zv="" s="Телеф." a="" du="8:22" c="11,4407" dup="9:00" f="13,5000" bd="05.09.2016 15:38:51" cur="810" gmt="+07:00" /><i d="06.09.2016 9:23:05" n="&lt;--79831245623" zp="" zv="" s="Телеф." a="" du="1:05" c="0" dup="1:05" f="0" bd="06.09.2016 9:29:09" cur="810" gmt="+07:00" /><i d="06.09.2016 9:47:46" n="internet.mts.ru" zp="" zv="" s="LTE (4G)" a="" du="206Kb" c="0" dup="300Kb" f="0" bd="06.09.2016 9:55:31" cur="810" gmt="+07:00" /><i d="06.09.2016 9:54:46" n="internet.mts.ru" zp="" zv="" s="HSDPA (3G)" a="" du="21Kb" c="0" dup="100Kb" f="0" bd="06.09.2016 10:02:28" cur="810" gmt="+07:00" /><i d="06.09.2016 12:33:07" n="internet.mts.ru" zp="" zv="" s="HSDPA (3G)" a="" du="4Kb" c="0" dup="100Kb" f="0" bd="06.09.2016 12:42:22" cur="810" gmt="+07:00" /><i d="06.09.2016 12:33:10" n="&lt;--79139112855" zp="" zv="" s="Телеф. (3G)" a="" du="0:50" c="0" dup="0:50" f="0" bd="06.09.2016 12:39:06" cur="810" gmt="+07:00" /><i d="06.09.2016 12:57:16" n="&lt;--79139112855" zp="" zv="" s="Телеф. (3G)" a="" du="0:04" c="0" dup="0:04" f="0" bd="06.09.2016 12:59:09" cur="810" gmt="+07:00" /><i d="06.09.2016 12:57:45" n="79139112855" zp="" zv="" s="Телеф." a="" du="0:19" c="0" dup="1:00" f="0" bd="06.09.2016 12:58:04" cur="810" gmt="+07:00" /><i d="06.09.2016 13:23:59" n="79139112855" zp="" zv="" s="Телеф." a="" du="0:29" c="0" dup="1:00" f="0" bd="06.09.2016 13:24:28" cur="810" gmt="+07:00" /><i d="06.09.2016 13:33:12" n="internet.mts.ru" zp="" zv="" s="HSDPA (3G)" a="" du="73Kb" c="0" dup="100Kb" f="0" bd="06.09.2016 13:41:28" cur="810" gmt="+07:00" /><i d="06.09.2016 14:23:18" n="&lt;--79137031775" zp="" zv="" s="Телеф. (3G)" a="" du="0:44" c="0" dup="0:44" f="0" bd="06.09.2016 14:29:22" cur="810" gmt="+07:00" /><i d="06.09.2016 14:33:12" n="internet.mts.ru" zp="" zv="" s="LTE (4G)" a="" du="67Kb" c="0" dup="100Kb" f="0" bd="06.09.2016 14:41:20" cur="810" gmt="+07:00" /><i d="06.09.2016 14:37:39" n="&lt;--sms:900" zp="" zv="" s="sms i" a="" du="0" c="0" dup="1" f="0" bd="06.09.2016 14:44:09" cur="810" gmt="+07:00" /><i d="06.09.2016 15:33:12" n="internet.mts.ru" zp="" zv="" s="LTE (4G)" a="" du="66Kb" c="0" dup="100Kb" f="0" bd="06.09.2016 15:41:24" cur="810" gmt="+07:00" /><i d="06.09.2016 17:24:40" n="3159999" zp="" zv="" s="Телеф." a="" du="1:54" c="2,5424" dup="2:00" f="3,0000" bd="06.09.2016 17:26:34" cur="810" gmt="+07:00" /><i d="06.09.2016 17:33:13" n="internet.mts.ru" zp="" zv="" s="LTE (4G)" a="" du="19Kb" c="0" dup="100Kb" f="0" bd="06.09.2016 17:41:20" cur="810" gmt="+07:00" /><i d="06.09.2016 18:33:13" n="internet.mts.ru" zp="" zv="" s="LTE (4G)" a="" du="227Kb" c="0" dup="300Kb" f="0" bd="06.09.2016 18:42:21" cur="810" gmt="+07:00" /><i d="06.09.2016 19:14:30" n="internet.mts.ru" zp="" zv="" s="LTE (4G)" a="" du="155Kb" c="0" dup="200Kb" f="0" bd="06.09.2016 19:22:17" cur="810" gmt="+07:00" /><i d="06.09.2016 19:33:13" n="internet.mts.ru" zp="" zv="" s="LTE (4G)" a="" du="64Kb" c="0" dup="100Kb" f="0" bd="06.09.2016 19:41:13" cur="810" gmt="+07:00" /><i d="06.09.2016 20:33:13" n="internet.mts.ru" zp="" zv="" s="LTE (4G)" a="" du="50Kb" c="0" dup="100Kb" f="0" bd="06.09.2016 20:41:18" cur="810" gmt="+07:00" /><i d="06.09.2016 21:01:35" n="&lt;--sms:Raiffeisen" zp="" zv="" s="sms i" a="" du="0" c="0" dup="1" f="0" bd="06.09.2016 21:03:53" cur="810" gmt="+07:00" /><i d="06.09.2016 21:01:36" n="&lt;--sms:Raiffeisen" zp="" zv="" s="sms i" a="" du="0" c="0" dup="1" f="0" bd="06.09.2016 21:03:53" cur="810" gmt="+07:00" /><i d="06.09.2016 21:01:37" n="&lt;--sms:Raiffeisen" zp="" zv="" s="sms i" a="" du="0" c="0" dup="1" f="0" bd="06.09.2016 21:03:53" cur="810" gmt="+07:00" /><i d="06.09.2016 21:01:38" n="&lt;--sms:Raiffeisen" zp="" zv="" s="sms i" a="" du="0" c="0" dup="1" f="0" bd="06.09.2016 21:03:53" cur="810" gmt="+07:00" /><i d="06.09.2016 23:55:00" n="Traffic_Category_900_033.001_G" zp="" zv="" s="LTE (4G)" a="" du="1Kb" c="0" dup="1Kb" f="0" bd="07.09.2016 0:02:10" cur="810" gmt="+07:00" /><i d="07.09.2016 7:48:58" n="internet.mts.ru" zp="" zv="" s="LTE (4G)" a="" du="74Kb" c="0" dup="100Kb" f="0" bd="07.09.2016 7:54:53" cur="810" gmt="+07:00" /><i d="07.09.2016 10:18:30" n="internet.mts.ru" zp="" zv="" s="gprs" a="" du="29Kb" c="0" dup="100Kb" f="0" bd="07.09.2016 10:25:11" cur="810" gmt="+07:00" /><i d="07.09.2016 17:41:22" n="internet.mts.ru" zp="" zv="" s="LTE (4G)" a="" du="67Kb" c="0" dup="100Kb" f="0" bd="07.09.2016 17:49:04" cur="810" gmt="+07:00" /><i d="07.09.2016 18:37:42" n="79831245623" zp="" zv="" s="Телеф." a="" du="0:58" c="0" dup="1:00" f="0" bd="07.09.2016 18:38:40" cur="810" gmt="+07:00" /><i d="07.09.2016 18:41:22" n="internet.mts.ru" zp="" zv="" s="LTE (4G)" a="" du="145Kb" c="0" dup="200Kb" f="0" bd="07.09.2016 18:49:14" cur="810" gmt="+07:00" /><i d="07.09.2016 19:35:15" n="79139247388" zp="" zv="" s="Телеф." a="" du="0:45" c="0" dup="1:00" f="0" bd="07.09.2016 19:36:00" cur="810" gmt="+07:00" /><i d="07.09.2016 19:41:22" n="internet.mts.ru" zp="" zv="" s="LTE (4G)" a="" du="1979Kb" c="0" dup="2000Kb" f="0" bd="07.09.2016 19:50:01" cur="810" gmt="+07:00" /><i d="07.09.2016 20:40:21" n="internet.mts.ru" zp="" zv="" s="LTE (4G)" a="" du="2052Kb" c="0" dup="2100Kb" f="0" bd="07.09.2016 20:49:00" cur="810" gmt="+07:00" /><i d="07.09.2016 20:41:22" n="internet.mts.ru" zp="" zv="" s="LTE (4G)" a="" du="1670Kb" c="0" dup="1700Kb" f="0" bd="07.09.2016 20:50:02" cur="810" gmt="+07:00" /><i d="07.09.2016 21:41:22" n="internet.mts.ru" zp="" zv="" s="LTE (4G)" a="" du="19Kb" c="0" dup="100Kb" f="0" bd="07.09.2016 21:49:52" cur="810" gmt="+07:00" /><i d="07.09.2016 22:41:22" n="internet.mts.ru" zp="" zv="" s="LTE (4G)" a="" du="1Kb" c="0" dup="100Kb" f="0" bd="07.09.2016 22:50:07" cur="810" gmt="+07:00" /><i d="08.09.2016 1:41:35" n="Traffic_Category_900_033.001_G" zp="" zv="" s="LTE (4G)" a="" du="1Kb" c="0" dup="1Kb" f="0" bd="08.09.2016 1:48:45" cur="810" gmt="+07:00" /><i d="08.09.2016 9:00:03" n="internet.mts.ru" zp="" zv="" s="LTE (4G)" a="" du="26Kb" c="0" dup="100Kb" f="0" bd="08.09.2016 9:07:18" cur="810" gmt="+07:00" /><i d="08.09.2016 9:23:32" n="internet.mts.ru" zp="" zv="" s="LTE (4G)" a="" du="43Kb" c="0" dup="100Kb" f="0" bd="08.09.2016 9:30:07" cur="810" gmt="+07:00" /><i d="08.09.2016 10:23:46" n="&lt;--sms:DNEVNIK.RU" zp="" zv="" s="sms i" a="" du="0" c="0" dup="1" f="0" bd="08.09.2016 10:29:02" cur="810" gmt="+07:00" /><i d="08.09.2016 10:24:14" n="internet.mts.ru" zp="" zv="" s="gprs" a="" du="17Kb" c="0" dup="100Kb" f="0" bd="08.09.2016 10:31:21" cur="810" gmt="+07:00" /><i d="08.09.2016 12:31:43" n="79831245623" zp="" zv="" s="Телеф." a="" du="0:21" c="0" dup="1:00" f="0" bd="08.09.2016 12:32:04" cur="810" gmt="+07:00" /><i d="08.09.2016 13:24:14" n="internet.mts.ru" zp="" zv="" s="LTE (4G)" a="" du="1Kb" c="0" dup="100Kb" f="0" bd="08.09.2016 13:32:31" cur="810" gmt="+07:00" /><i d="08.09.2016 13:46:42" n="&lt;--79139112855" zp="" zv="" s="Телеф. (3G)" a="" du="0:08" c="0" dup="0:08" f="0" bd="08.09.2016 13:49:25" cur="810" gmt="+07:00" /><i d="08.09.2016 14:00:23" n="&lt;--79139112855" zp="" zv="" s="Телеф. (3G)" a="" du="3:44" c="0" dup="3:44" f="0" bd="08.09.2016 14:09:27" cur="810" gmt="+07:00" /><i d="08.09.2016 14:24:14" n="internet.mts.ru" zp="" zv="" s="LTE (4G)" a="" du="292Kb" c="0" dup="300Kb" f="0" bd="08.09.2016 14:32:16" cur="810" gmt="+07:00" /><i d="08.09.2016 14:47:30" n="internet.mts.ru" zp="" zv="" s="LTE (4G)" a="" du="33Kb" c="0" dup="100Kb" f="0" bd="08.09.2016 14:55:16" cur="810" gmt="+07:00" /><i d="08.09.2016 15:24:14" n="internet.mts.ru" zp="" zv="" s="LTE (4G)" a="" du="4Kb" c="0" dup="100Kb" f="0" bd="08.09.2016 15:32:22" cur="810" gmt="+07:00" /><i d="08.09.2016 16:38:36" n="&lt;--sms:ThomasMunz" zp="" zv="" s="sms i" a="" du="0" c="0" dup="1" f="0" bd="08.09.2016 16:44:15" cur="810" gmt="+07:00" /><i d="08.09.2016 16:50:12" n="&lt;--79831245623" zp="" zv="" s="Телеф. (3G)" a="" du="5:07" c="0" dup="5:07" f="0" bd="08.09.2016 16:59:13" cur="810" gmt="+07:00" /><i d="08.09.2016 17:13:43" n="124" zp="" zv="" s="Телеф." a="" du="1:38" c="0" dup="2:00" f="0" bd="08.09.2016 17:15:21" cur="810" gmt="+07:00" /><i d="08.09.2016 17:37:07" n="&lt;--79139112855" zp="" zv="" s="Телеф. (3G)" a="" du="2:10" c="0" dup="2:10" f="0" bd="08.09.2016 17:44:17" cur="810" gmt="+07:00" /><i d="08.09.2016 21:38:37" n="&lt;--79618783178" zp="" zv="" s="Телеф. (3G)" a="" du="14:05" c="0" dup="14:05" f="0" bd="08.09.2016 21:58:34" cur="810" gmt="+07:00" /><i d="09.09.2016 8:31:36" n="&lt;--79831245623" zp="" zv="" s="Телеф. (3G)" a="" du="1:44" c="0" dup="1:44" f="0" bd="09.09.2016 8:38:39" cur="810" gmt="+07:00" /><i d="09.09.2016 9:17:39" n="internet.mts.ru" zp="" zv="" s="LTE (4G)" a="" du="13Kb" c="0" dup="100Kb" f="0" bd="09.09.2016 9:24:15" cur="810" gmt="+07:00" /><i d="09.09.2016 10:38:23" n="79831245623" zp="" zv="" s="Телеф." a="" du="0:08" c="0" dup="1:00" f="0" bd="09.09.2016 10:38:31" cur="810" gmt="+07:00" /><i d="09.09.2016 10:44:04" n="3369090" zp="" zv="" s="Телеф." a="" du="0:22" c="1,2712" dup="1:00" f="1,5000" bd="09.09.2016 10:44:26" cur="810" gmt="+07:00" /><i d="09.09.2016 10:45:44" n="&lt;--79133712345" zp="" zv="" s="Телеф. (3G)" a="" du="0:15" c="0" dup="0:15" f="0" bd="09.09.2016 10:49:19" cur="810" gmt="+07:00" /><i d="09.09.2016 11:05:05" n="internet.mts.ru" zp="" zv="" s="LTE (4G)" a="" du="651Kb" c="0" dup="700Kb" f="0" bd="09.09.2016 11:13:59" cur="810" gmt="+07:00" /><i d="09.09.2016 12:02:26" n="internet.mts.ru" zp="" zv="" s="LTE (4G)" a="" du="6869Kb" c="0" dup="6900Kb" f="0" bd="09.09.2016 12:11:25" cur="810" gmt="+07:00" /><i d="09.09.2016 12:05:05" n="internet.mts.ru" zp="" zv="" s="LTE (4G)" a="" du="5523Kb" c="0" dup="5600Kb" f="0" bd="09.09.2016 12:14:21" cur="810" gmt="+07:00" /><i d="09.09.2016 12:48:48" n="79137031775" zp="" zv="" s="Телеф." a="" du="1:00" c="0" g="b" dup="1:00" f="0" bd="09.09.2016 12:49:48" cur="810" gmt="+07:00" /><i d="09.09.2016 12:49:10" n="internet.mts.ru" zp="" zv="" s="LTE (4G)" a="" du="197Kb" c="0" g="e" dup="200Kb" f="0" bd="09.09.2016 12:58:10" cur="810" gmt="+07:00" /><i d="09.09.2016 13:49:51" n="internet.mts.ru" zp="" zv="" s="LTE (4G)" a="" du="44Kb" c="0" dup="100Kb" f="0" bd="09.09.2016 13:58:12" cur="810" gmt="+07:00" /><i d="09.09.2016 14:49:51" n="internet.mts.ru" zp="" zv="" s="LTE (4G)" a="" du="25Kb" c="0" dup="100Kb" f="0" bd="09.09.2016 14:58:21" cur="810" gmt="+07:00" /><i d="09.09.2016 15:10:36" n="79139112855" zp="" zv="" s="Телеф." a="" du="0:51" c="0" dup="1:00" f="0" bd="09.09.2016 15:11:27" cur="810" gmt="+07:00" /><i d="09.09.2016 16:49:51" n="internet.mts.ru" zp="" zv="" s="LTE (4G)" a="" du="69Kb" c="0" dup="100Kb" f="0" bd="09.09.2016 16:58:09" cur="810" gmt="+07:00" /><i d="09.09.2016 16:50:25" n="&lt;--79831245623" zp="" zv="" s="Телеф. (3G)" a="" du="0:37" c="0" dup="0:37" f="0" bd="09.09.2016 16:53:59" cur="810" gmt="+07:00" /><i d="09.09.2016 17:49:51" n="internet.mts.ru" zp="" zv="" s="LTE (4G)" a="" du="25Kb" c="0" dup="100Kb" f="0" bd="09.09.2016 17:57:33" cur="810" gmt="+07:00" /><i d="09.09.2016 17:54:42" n="3813119" zp="" zv="" s="Телеф." a="" du="1:32" c="2,5424" dup="2:00" f="3,0000" bd="09.09.2016 17:56:14" cur="810" gmt="+07:00" /><i d="09.09.2016 18:49:51" n="internet.mts.ru" zp="" zv="" s="LTE (4G)" a="" du="1201Kb" c="0" dup="1300Kb" f="0" bd="09.09.2016 18:57:28" cur="810" gmt="+07:00" /><i d="09.09.2016 18:54:03" n="internet.mts.ru" zp="" zv="" s="LTE (4G)" a="" du="348Kb" c="0" dup="400Kb" f="0" bd="09.09.2016 19:01:22" cur="810" gmt="+07:00" /><i d="09.09.2016 19:44:03" n="&lt;--79213284829" zp="" zv="" s="Телеф. (3G)" a="" du="0:21" c="0" dup="0:21" f="0" bd="09.09.2016 19:48:52" cur="810" gmt="+07:00" /><i d="09.09.2016 19:49:51" n="internet.mts.ru" zp="" zv="" s="LTE (4G)" a="" du="2Kb" c="0" dup="100Kb" f="0" bd="09.09.2016 19:57:21" cur="810" gmt="+07:00" /><i d="09.09.2016 20:28:20" n="79831245623" zp="" zv="" s="Телеф." a="" du="35:39" c="0" dup="36:00" f="0" bd="09.09.2016 21:03:59" cur="810" gmt="+07:00" /><i d="10.09.2016 10:04:23" n="124" zp="" zv="" s="Телеф." a="" du="1:25" c="0" dup="2:00" f="0" bd="10.09.2016 10:05:48" cur="810" gmt="+07:00" /><i d="10.09.2016 11:08:08" n="79831245623" zp="" zv="" s="Телеф." a="" du="1:53" c="0" dup="2:00" f="0" bd="10.09.2016 11:10:01" cur="810" gmt="+07:00" /><i d="10.09.2016 13:04:36" n="internet.mts.ru" zp="" zv="" s="LTE (4G)" a="" du="724Kb" c="0" dup="800Kb" f="0" bd="10.09.2016 13:12:12" cur="810" gmt="+07:00" /><i d="10.09.2016 14:04:36" n="internet.mts.ru" zp="" zv="" s="LTE (4G)" a="" du="271Kb" c="0" dup="300Kb" f="0" bd="10.09.2016 14:12:16" cur="810" gmt="+07:00" /><i d="10.09.2016 15:04:36" n="internet.mts.ru" zp="" zv="" s="LTE (4G)" a="" du="2Kb" c="0" dup="100Kb" f="0" bd="10.09.2016 15:12:18" cur="810" gmt="+07:00" /><i d="10.09.2016 17:50:39" n="&lt;--79831245623" zp="" zv="" s="Телеф. (3G)" a="" du="0:47" c="0" dup="0:47" f="0" bd="10.09.2016 17:53:42" cur="810" gmt="+07:00" /><i d="10.09.2016 18:04:36" n="internet.mts.ru" zp="" zv="" s="LTE (4G)" a="" du="86Kb" c="0" dup="100Kb" f="0" bd="10.09.2016 18:12:05" cur="810" gmt="+07:00" /><i d="10.09.2016 19:12:31" n="&lt;--79831245623" zp="" zv="" s="Телеф. (3G)" a="" du="0:14" c="0" dup="0:14" f="0" bd="10.09.2016 19:18:51" cur="810" gmt="+07:00" /><i d="10.09.2016 21:47:44" n="79831245623" zp="" zv="" s="Телеф." a="" du="0:09" c="0" dup="1:00" f="0" bd="10.09.2016 21:47:53" cur="810" gmt="+07:00" /><i d="11.09.2016 11:03:19" n="3803120" zp="" zv="" s="Телеф." a="" du="0:28" c="1,2712" dup="1:00" f="1,5000" bd="11.09.2016 11:03:47" cur="810" gmt="+07:00" /><i d="11.09.2016 11:28:32" n="79831245623" zp="" zv="" s="Телеф." a="" du="4:49" c="0" dup="5:00" f="0" bd="11.09.2016 11:33:21" cur="810" gmt="+07:00" /><i d="11.09.2016 12:51:23" n="&lt;--sms:900" zp="" zv="" s="sms i" a="" du="0" c="0" dup="1" f="0" bd="11.09.2016 12:53:39" cur="810" gmt="+07:00" /><i d="11.09.2016 12:51:24" n="&lt;--sms:900" zp="" zv="" s="sms i" a="" du="0" c="0" dup="1" f="0" bd="11.09.2016 12:53:39" cur="810" gmt="+07:00" /><i d="11.09.2016 13:05:03" n="&lt;--79139247388" zp="" zv="" s="Телеф. (3G)" a="" du="0:29" c="0" dup="0:29" f="0" bd="11.09.2016 13:08:42" cur="810" gmt="+07:00" /><i d="11.09.2016 13:51:28" n="internet.mts.ru" zp="" zv="" s="LTE (4G)" a="" du="72Kb" c="0" dup="100Kb" f="0" bd="11.09.2016 13:59:08" cur="810" gmt="+07:00" /><i d="11.09.2016 14:51:28" n="internet.mts.ru" zp="" zv="" s="LTE (4G)" a="" du="17Kb" c="0" dup="100Kb" f="0" bd="11.09.2016 14:59:16" cur="810" gmt="+07:00" /><i d="11.09.2016 20:25:25" n="internet.mts.ru" zp="" zv="" s="LTE (4G)" a="" du="25Kb" c="0" dup="100Kb" f="0" bd="11.09.2016 20:33:08" cur="810" gmt="+07:00" /><i d="12.09.2016 8:54:47" n="internet.mts.ru" zp="" zv="" s="LTE (4G)" a="" du="230Kb" c="0" dup="300Kb" f="0" bd="12.09.2016 9:01:08" cur="810" gmt="+07:00" /><i d="12.09.2016 11:11:16" n="79831245623" zp="" zv="" s="Телеф." a="" du="2:26" c="0" g="b" dup="3:00" f="0" bd="12.09.2016 11:13:42" cur="810" gmt="+07:00" /><i d="12.09.2016 11:11:59" n="internet.mts.ru" zp="" zv="" s="LTE (4G)" a="" du="92Kb" c="0" g="e" dup="100Kb" f="0" bd="12.09.2016 11:19:16" cur="810" gmt="+07:00" /><i d="12.09.2016 11:44:56" n="&lt;--79137031775" zp="" zv="" s="Телеф. (3G)" a="" du="1:53" c="0" dup="1:53" f="0" bd="12.09.2016 11:49:26" cur="810" gmt="+07:00" /><i d="12.09.2016 12:11:59" n="internet.mts.ru" zp="" zv="" s="HSDPA (3G)" a="" du="55Kb" c="0" dup="100Kb" f="0" bd="12.09.2016 12:19:18" cur="810" gmt="+07:00" /><i d="12.09.2016 13:11:59" n="internet.mts.ru" zp="" zv="" s="LTE (4G)" a="" du="381Kb" c="0" dup="400Kb" f="0" bd="12.09.2016 13:19:27" cur="810" gmt="+07:00" /><i d="12.09.2016 13:28:57" n="internet.mts.ru" zp="" zv="" s="LTE (4G)" a="" du="332Kb" c="0" dup="400Kb" f="0" bd="12.09.2016 13:36:22" cur="810" gmt="+07:00" /><i d="12.09.2016 14:11:59" n="internet.mts.ru" zp="" zv="" s="LTE (4G)" a="" du="16Kb" c="0" dup="100Kb" f="0" bd="12.09.2016 14:19:29" cur="810" gmt="+07:00" /><i d="12.09.2016 15:12:00" n="internet.mts.ru" zp="" zv="" s="LTE (4G)" a="" du="163Kb" c="0" dup="200Kb" f="0" bd="12.09.2016 15:20:12" cur="810" gmt="+07:00" /><i d="12.09.2016 15:28:57" n="internet.mts.ru" zp="" zv="" s="LTE (4G)" a="" du="7129Kb" c="0" dup="7200Kb" f="0" bd="12.09.2016 15:37:24" cur="810" gmt="+07:00" /><i d="12.09.2016 15:29:22" n="79139247388" zp="" zv="" s="sms o" a="" du="1" c="0" dup="1" f="0" bd="12.09.2016 15:29:23" cur="810" gmt="+07:00" /><i d="12.09.2016 15:33:38" n="79831245623" zp="" zv="" s="Телеф." a="" du="5:49" c="0" g="b" dup="6:00" f="0" bd="12.09.2016 15:39:27" cur="810" gmt="+07:00" /><i d="12.09.2016 15:33:58" n="internet.mts.ru" zp="" zv="" s="LTE (4G)" a="" du="1526Kb" c="0" g="i" dup="1600Kb" f="0" bd="12.09.2016 15:42:22" cur="810" gmt="+07:00" /><i d="12.09.2016 15:33:58" n="Traffic_Category_900_033.001_G" zp="" zv="" s="LTE (4G)" a="" du="1Kb" c="0" g="i" dup="1Kb" f="0" bd="12.09.2016 15:42:11" cur="810" gmt="+07:00" /><i d="12.09.2016 15:33:58" n="internet.mts.ru" zp="" zv="" s="LTE (4G)" a="" du="3Kb" c="0" g="e" dup="100Kb" f="0" bd="12.09.2016 15:42:20" cur="810" gmt="+07:00" /><i d="12.09.2016 16:40:01" n="internet.mts.ru" zp="" zv="" s="LTE (4G)" a="" du="11722Kb" c="0" dup="11800Kb" f="0" bd="12.09.2016 16:48:04" cur="810" gmt="+07:00" /><i d="12.09.2016 17:30:54" n="internet.mts.ru" zp="" zv="" s="LTE (4G)" a="" du="15226Kb" c="0" dup="15300Kb" f="0" bd="12.09.2016 17:39:14" cur="810" gmt="+07:00" /><i d="12.09.2016 17:40:01" n="internet.mts.ru" zp="" zv="" s="LTE (4G)" a="" du="5230Kb" c="0" dup="5300Kb" f="0" bd="12.09.2016 17:48:19" cur="810" gmt="+07:00" /><i d="12.09.2016 18:27:26" n="&lt;--sms:900" zp="" zv="" s="sms i" a="" du="0" c="0" dup="1" f="0" bd="12.09.2016 18:30:05" cur="810" gmt="+07:00" /><i d="12.09.2016 18:27:27" n="&lt;--sms:900" zp="" zv="" s="sms i" a="" du="0" c="0" dup="1" f="0" bd="12.09.2016 18:30:05" cur="810" gmt="+07:00" /><i d="12.09.2016 18:30:54" n="internet.mts.ru" zp="" zv="" s="LTE (4G)" a="" du="2Kb" c="0" dup="100Kb" f="0" bd="12.09.2016 18:39:16" cur="810" gmt="+07:00" /><i d="12.09.2016 18:39:58" n="internet.mts.ru" zp="" zv="" s="LTE (4G)" a="" du="1092Kb" c="0" dup="1100Kb" f="0" bd="12.09.2016 18:48:01" cur="810" gmt="+07:00" /><i d="12.09.2016 19:39:58" n="internet.mts.ru" zp="" zv="" s="HSDPA (3G)" a="" du="76Kb" c="0" dup="100Kb" f="0" bd="12.09.2016 19:47:52" cur="810" gmt="+07:00" /><i d="12.09.2016 20:39:58" n="internet.mts.ru" zp="" zv="" s="LTE (4G)" a="" du="17Kb" c="0" dup="100Kb" f="0" bd="12.09.2016 20:48:00" cur="810" gmt="+07:00" /><i d="12.09.2016 21:26:55" n="79831245623" zp="" zv="" s="Телеф." a="" du="1:32" c="0" dup="2:00" f="0" bd="12.09.2016 21:28:27" cur="810" gmt="+07:00" /><i d="12.09.2016 21:29:09" n="&lt;--74957757500" zp="" zv="" s="Телеф. (3G)" a="" du="0:31" c="0" dup="0:31" f="0" bd="12.09.2016 21:33:35" cur="810" gmt="+07:00" /><i d="13.09.2016 0:02:52" n="Traffic_Category_900_033.001_G" zp="" zv="" s="LTE (4G)" a="" du="2Kb" c="0" dup="2Kb" f="0" bd="13.09.2016 0:10:06" cur="810" gmt="+07:00" /><i d="13.09.2016 7:56:19" n="internet.mts.ru" zp="" zv="" s="HSDPA (3G)" a="" du="65Kb" c="0" dup="100Kb" f="0" bd="13.09.2016 8:02:18" cur="810" gmt="+07:00" /><i d="13.09.2016 8:06:16" n="internet.mts.ru" zp="" zv="" s="HSDPA (3G)" a="" du="7Kb" c="0" dup="100Kb" f="0" bd="13.09.2016 8:13:00" cur="810" gmt="+07:00" /><i d="13.09.2016 9:17:27" n="internet.mts.ru" zp="" zv="" s="LTE (4G)" a="" du="99Kb" c="0" dup="100Kb" f="0" bd="13.09.2016 9:24:03" cur="810" gmt="+07:00" /><i d="13.09.2016 11:03:43" n="internet.mts.ru" zp="" zv="" s="LTE (4G)" a="" du="91Kb" c="0" dup="100Kb" f="0" bd="13.09.2016 11:11:11" cur="810" gmt="+07:00" /><i d="13.09.2016 11:47:42" n="79831245623" zp="" zv="" s="Телеф." a="" du="1:02" c="0" dup="2:00" f="0" bd="13.09.2016 11:48:44" cur="810" gmt="+07:00" /><i d="13.09.2016 12:24:49" n="internet.mts.ru" zp="" zv="" s="LTE (4G)" a="" du="114Kb" c="0" dup="200Kb" f="0" bd="13.09.2016 12:32:17" cur="810" gmt="+07:00" /><i d="13.09.2016 14:13:55" n="internet.mts.ru" zp="" zv="" s="LTE (4G)" a="" du="5773Kb" c="0" dup="5800Kb" f="0" bd="13.09.2016 14:21:26" cur="810" gmt="+07:00" /><i d="13.09.2016 14:21:14" n="internet.mts.ru" zp="" zv="" s="LTE (4G)" a="" du="3298Kb" c="0" dup="3300Kb" f="0" bd="13.09.2016 14:29:02" cur="810" gmt="+07:00" /><i d="13.09.2016 15:03:08" n="79831245623" zp="" zv="" s="Телеф." a="" du="4:23" c="0" dup="5:00" f="0" bd="13.09.2016 15:07:31" cur="810" gmt="+07:00" /><i d="13.09.2016 15:26:11" n="internet.mts.ru" zp="" zv="" s="LTE (4G)" a="" du="32Kb" c="0" dup="100Kb" f="0" bd="13.09.2016 15:34:19" cur="810" gmt="+07:00" /><i d="13.09.2016 16:23:00" n="internet.mts.ru" zp="" zv="" s="LTE (4G)" a="" du="2538Kb" c="0" dup="2600Kb" f="0" bd="13.09.2016 16:30:12" cur="810" gmt="+07:00" /><i d="13.09.2016 16:37:17" n="internet.mts.ru" zp="" zv="" s="LTE (4G)" a="" du="25Kb" c="0" dup="100Kb" f="0" bd="13.09.2016 16:45:12" cur="810" gmt="+07:00" /><i d="13.09.2016 17:02:00" n="Traffic_Category_900_033.001_G" zp="" zv="" s="HSDPA (3G)" a="" du="1Kb" c="0" dup="1Kb" f="0" bd="13.09.2016 17:09:09" cur="810" gmt="+07:00" /><i d="13.09.2016 18:04:34" n="&lt;--sms:RiveGauche" zp="" zv="" s="sms i" a="" du="0" c="0" dup="1" f="0" bd="13.09.2016 18:10:12" cur="810" gmt="+07:00" /><i d="13.09.2016 18:04:35" n="&lt;--sms:RiveGauche" zp="" zv="" s="sms i" a="" du="0" c="0" dup="1" f="0" bd="13.09.2016 18:10:12" cur="810" gmt="+07:00" /><i d="13.09.2016 18:11:09" n="internet.mts.ru" zp="" zv="" s="LTE (4G)" a="" du="65Kb" c="0" dup="100Kb" f="0" bd="13.09.2016 18:19:12" cur="810" gmt="+07:00" /><i d="13.09.2016 19:15:27" n="internet.mts.ru" zp="" zv="" s="LTE (4G)" a="" du="199Kb" c="0" dup="200Kb" f="0" bd="13.09.2016 19:23:07" cur="810" gmt="+07:00" /><i d="13.09.2016 20:20:57" n="internet.mts.ru" zp="" zv="" s="HSDPA (3G)" a="" du="2044Kb" c="0" dup="2100Kb" f="0" bd="13.09.2016 20:27:57" cur="810" gmt="+07:00" /><i d="13.09.2016 20:21:06" n="&lt;--79139112855" zp="" zv="" s="Телеф. (3G)" a="" du="20:25" c="0" dup="20:25" f="0" bd="13.09.2016 20:43:54" cur="810" gmt="+07:00" /><i d="13.09.2016 23:50:58" n="Traffic_Category_900_033.001_G" zp="" zv="" s="LTE (4G)" a="" du="1Kb" c="0" dup="1Kb" f="0" bd="13.09.2016 23:58:00" cur="810" gmt="+07:00" /><i d="14.09.2016 9:29:10" n="internet.mts.ru" zp="" zv="" s="LTE (4G)" a="" du="1665Kb" c="0" dup="1700Kb" f="0" bd="14.09.2016 9:37:15" cur="810" gmt="+07:00" /><i d="14.09.2016 10:06:04" n="&lt;--79831245623" zp="" zv="" s="Телеф. (3G)" a="" du="2:56" c="0" dup="2:56" f="0" bd="14.09.2016 10:14:18" cur="810" gmt="+07:00" /><i d="14.09.2016 10:09:08" n="internet.mts.ru" zp="" zv="" s="LTE (4G)" a="" du="703Kb" c="0" g="b" dup="800Kb" f="0" bd="14.09.2016 10:17:25" cur="810" gmt="+07:00" /><i d="14.09.2016 10:09:08" n="internet.mts.ru" zp="" zv="" s="LTE (4G)" a="" du="1167Kb" c="0" g="e" dup="1200Kb" f="0" bd="14.09.2016 10:17:25" cur="810" gmt="+07:00" /><i d="14.09.2016 11:52:50" n="internet.mts.ru" zp="" zv="" s="LTE (4G)" a="" du="752Kb" c="0" dup="800Kb" f="0" bd="14.09.2016 12:01:20" cur="810" gmt="+07:00" /><i d="14.09.2016 12:46:32" n="internet.mts.ru" zp="" zv="" s="LTE (4G)" a="" du="2827Kb" c="0" dup="2900Kb" f="0" bd="14.09.2016 12:54:29" cur="810" gmt="+07:00" /><i d="14.09.2016 13:23:44" n="internet.mts.ru" zp="" zv="" s="LTE (4G)" a="" du="3472Kb" c="0" dup="3500Kb" f="0" bd="14.09.2016 13:31:32" cur="810" gmt="+07:00" /><i d="14.09.2016 13:50:25" n="internet.mts.ru" zp="" zv="" s="LTE (4G)" a="" du="1424Kb" c="0" dup="1500Kb" f="0" bd="14.09.2016 13:58:23" cur="810" gmt="+07:00" /><i d="14.09.2016 14:17:47" n="&lt;--79831245623" zp="" zv="" s="Телеф. (3G)" a="" du="0:22" c="0" dup="0:22" f="0" bd="14.09.2016 14:24:08" cur="810" gmt="+07:00" /><i d="14.09.2016 14:18:26" n="Traffic_Category_900_033.001_G" zp="" zv="" s="LTE (4G)" a="" du="1Kb" c="0" g="b" dup="1Kb" f="0" bd="14.09.2016 14:26:34" cur="810" gmt="+07:00" /><i d="14.09.2016 14:18:26" n="internet.mts.ru" zp="" zv="" s="LTE (4G)" a="" du="220Kb" c="0" g="e" dup="300Kb" f="0" bd="14.09.2016 14:26:37" cur="810" gmt="+07:00" /><i d="14.09.2016 14:18:39" n="79139112855" zp="" zv="" s="Телеф." a="" du="1:14" c="0" dup="2:00" f="0" bd="14.09.2016 14:19:53" cur="810" gmt="+07:00" /><i d="14.09.2016 14:22:46" n="&lt;--79139112855" zp="" zv="" s="Телеф. (3G)" a="" du="0:15" c="0" dup="0:15" f="0" bd="14.09.2016 14:30:26" cur="810" gmt="+07:00" /><i d="14.09.2016 14:24:00" n="79139112855" zp="" zv="" s="Телеф." a="" du="9:31" c="0" g="b" dup="10:00" f="0" bd="14.09.2016 14:33:31" cur="810" gmt="+07:00" /><i d="14.09.2016 14:25:37" n="internet.mts.ru" zp="" zv="" s="LTE (4G)" a="" du="11Kb" c="0" g="e" dup="100Kb" f="0" bd="14.09.2016 14:33:23" cur="810" gmt="+07:00" /><i d="14.09.2016 15:39:29" n="internet.mts.ru" zp="" zv="" s="LTE (4G)" a="" du="6108Kb" c="0" dup="6200Kb" f="0" bd="14.09.2016 15:47:14" cur="810" gmt="+07:00" /><i d="14.09.2016 16:09:04" n="&lt;--sms:Svoya Comp" zp="" zv="" s="sms i" a="" du="0" c="0" dup="1" f="0" bd="14.09.2016 16:15:21" cur="810" gmt="+07:00" /><i d="14.09.2016 16:09:05" n="&lt;--sms:Svoya Comp" zp="" zv="" s="sms i" a="" du="0" c="0" dup="1" f="0" bd="14.09.2016 16:15:21" cur="810" gmt="+07:00" /><i d="14.09.2016 16:24:00" n="internet.mts.ru" zp="" zv="" s="LTE (4G)" a="" du="11785Kb" c="0" dup="11800Kb" f="0" bd="14.09.2016 16:31:12" cur="810" gmt="+07:00" /><i d="14.09.2016 16:42:23" n="internet.mts.ru" zp="" zv="" s="LTE (4G)" a="" du="2331Kb" c="0" dup="2400Kb" f="0" bd="14.09.2016 16:50:12" cur="810" gmt="+07:00" /><i d="14.09.2016 16:52:35" n="2276227" zp="" zv="" s="Телеф." a="" du="2:08" c="3,8136" dup="3:00" f="4,5000" bd="14.09.2016 16:54:43" cur="810" gmt="+07:00" /><i d="14.09.2016 17:09:11" n="79831245623" zp="" zv="" s="Телеф." a="" du="5:15" c="0" dup="6:00" f="0" bd="14.09.2016 17:14:26" cur="810" gmt="+07:00" /><i d="14.09.2016 17:14:52" n="79139112855" zp="" zv="" s="Телеф." a="" du="0:50" c="0" dup="1:00" f="0" bd="14.09.2016 17:15:42" cur="810" gmt="+07:00" /><i d="14.09.2016 17:16:01" n="79139112855" zp="" zv="" s="Телеф." a="" du="0:09" c="0" dup="1:00" f="0" bd="14.09.2016 17:16:10" cur="810" gmt="+07:00" /><i d="14.09.2016 17:16:54" n="79139112855" zp="" zv="" s="Телеф." a="" du="19:39" c="0" dup="20:00" f="0" bd="14.09.2016 17:36:33" cur="810" gmt="+07:00" /><i d="14.09.2016 17:36:42" n="internet.mts.ru" zp="" zv="" s="LTE (4G)" a="" du="1420Kb" c="0" dup="1500Kb" f="0" bd="14.09.2016 17:44:15" cur="810" gmt="+07:00" /><i d="14.09.2016 18:00:53" n="internet.mts.ru" zp="" zv="" s="LTE (4G)" a="" du="14Kb" c="0" dup="100Kb" f="0" bd="14.09.2016 18:08:21" cur="810" gmt="+07:00" /><i d="14.09.2016 18:51:05" n="internet.mts.ru" zp="" zv="" s="gprs" a="" du="261Kb" c="0" dup="300Kb" f="0" bd="14.09.2016 18:58:06" cur="810" gmt="+07:00" /><i d="14.09.2016 18:51:45" n="Traffic_Category_900_033.001_G" zp="" zv="" s="LTE (4G)" a="" du="1Kb" c="0" dup="1Kb" f="0" bd="14.09.2016 18:59:07" cur="810" gmt="+07:00" /><i d="14.09.2016 19:24:17" n="&lt;--sms:900" zp="" zv="" s="sms i" a="" du="0" c="0" dup="1" f="0" bd="14.09.2016 19:30:10" cur="810" gmt="+07:00" /><i d="14.09.2016 19:24:18" n="&lt;--sms:900" zp="" zv="" s="sms i" a="" du="0" c="0" dup="1" f="0" bd="14.09.2016 19:30:10" cur="810" gmt="+07:00" /><i d="14.09.2016 19:49:04" n="internet.mts.ru" zp="" zv="" s="LTE (4G)" a="" du="63Kb" c="0" dup="100Kb" f="0" bd="14.09.2016 19:55:21" cur="810" gmt="+07:00" /><i d="14.09.2016 19:54:20" n="internet.mts.ru" zp="" zv="" s="gprs" a="" du="8Kb" c="0" dup="100Kb" f="0" bd="14.09.2016 20:02:26" cur="810" gmt="+07:00" /><i d="14.09.2016 20:12:50" n="&lt;--79831245623" zp="" zv="" s="Телеф. (3G)" a="" du="3:11" c="0" dup="3:11" f="0" bd="14.09.2016 20:19:50" cur="810" gmt="+07:00" /><i d="14.09.2016 20:27:40" n="79139112855" zp="" zv="" s="Телеф." a="" du="9:34" c="0" dup="10:00" f="0" bd="14.09.2016 20:37:14" cur="810" gmt="+07:00" /><i d="14.09.2016 21:18:14" n="internet.mts.ru" zp="" zv="" s="LTE (4G)" a="" du="984Kb" c="0" dup="1000Kb" f="0" bd="14.09.2016 21:26:17" cur="810" gmt="+07:00" /><i d="15.09.2016 8:37:59" n="internet.mts.ru" zp="" zv="" s="HSDPA (3G)" a="" du="127Kb" c="0" dup="200Kb" f="0" bd="15.09.2016 8:43:25" cur="810" gmt="+07:00" /><i d="15.09.2016 9:48:30" n="internet.mts.ru" zp="" zv="" s="gprs" a="" du="71Kb" c="0" dup="100Kb" f="0" bd="15.09.2016 9:55:28" cur="810" gmt="+07:00" /><i d="15.09.2016 9:48:40" n="79831245623" zp="" zv="" s="Телеф." a="" du="1:30" c="0" dup="2:00" f="0" bd="15.09.2016 9:50:10" cur="810" gmt="+07:00" /><i d="15.09.2016 11:11:38" n="internet.mts.ru" zp="" zv="" s="HSDPA (3G)" a="" du="117Kb" c="0" dup="200Kb" f="0" bd="15.09.2016 11:19:17" cur="810" gmt="+07:00" /><i d="15.09.2016 12:06:09" n="&lt;--sms:RiveGauche" zp="" zv="" s="sms i" a="" du="0" c="0" dup="1" f="0" bd="15.09.2016 12:10:15" cur="810" gmt="+07:00" /><i d="15.09.2016 12:06:10" n="&lt;--sms:RiveGauche" zp="" zv="" s="sms i" a="" du="0" c="0" dup="1" f="0" bd="15.09.2016 12:10:15" cur="810" gmt="+07:00" /><i d="15.09.2016 12:37:46" n="internet.mts.ru" zp="" zv="" s="LTE (4G)" a="" du="361Kb" c="0" dup="400Kb" f="0" bd="15.09.2016 12:45:17" cur="810" gmt="+07:00" /><i d="15.09.2016 13:51:47" n="internet.mts.ru" zp="" zv="" s="gprs" a="" du="56Kb" c="0" dup="100Kb" f="0" bd="15.09.2016 13:59:17" cur="810" gmt="+07:00" /><i d="15.09.2016 13:52:03" n="79139247388" zp="" zv="" s="Телеф." a="" du="0:43" c="0" dup="1:00" f="0" bd="15.09.2016 13:52:46" cur="810" gmt="+07:00" /><i d="15.09.2016 15:08:20" n="internet.mts.ru" zp="" zv="" s="HSDPA (3G)" a="" du="96Kb" c="0" dup="100Kb" f="0" bd="15.09.2016 15:16:27" cur="810" gmt="+07:00" /><i d="15.09.2016 15:52:09" n="&lt;--79831245623" zp="" zv="" s="Телеф. (3G)" a="" du="2:32" c="0" g="b" dup="2:32" f="0" bd="15.09.2016 16:00:10" cur="810" gmt="+07:00" /><i d="15.09.2016 15:54:00" n="internet.mts.ru" zp="" zv="" s="LTE (4G)" a="" du="41Kb" c="0" g="e" dup="100Kb" f="0" bd="15.09.2016 16:00:32" cur="810" gmt="+07:00" /><i d="15.09.2016 17:03:26" n="internet.mts.ru" zp="" zv="" s="LTE (4G)" a="" du="30Kb" c="0" dup="100Kb" f="0" bd="15.09.2016 17:11:21" cur="810" gmt="+07:00" /><i d="15.09.2016 18:03:16" n="internet.mts.ru" zp="" zv="" s="LTE (4G)" a="" du="58Kb" c="0" dup="100Kb" f="0" bd="15.09.2016 18:11:11" cur="810" gmt="+07:00" /><i d="15.09.2016 18:03:24" n="79831245623" zp="" zv="" s="Телеф." a="" du="0:57" c="0" g="b" dup="1:00" f="0" bd="15.09.2016 18:04:21" cur="810" gmt="+07:00" /><i d="15.09.2016 18:04:00" n="internet.mts.ru" zp="" zv="" s="HSDPA (3G)" a="" du="4Kb" c="0" g="e" dup="100Kb" f="0" bd="15.09.2016 18:11:06" cur="810" gmt="+07:00" /><i d="15.09.2016 18:04:44" n="79139112855" zp="" zv="" s="Телеф." a="" du="2:03" c="0" g="b" dup="3:00" f="0" bd="15.09.2016 18:06:47" cur="810" gmt="+07:00" /><i d="15.09.2016 18:05:31" n="internet.mts.ru" zp="" zv="" s="HSDPA (3G)" a="" du="17Kb" c="0" g="e" dup="100Kb" f="0" bd="15.09.2016 18:13:02" cur="810" gmt="+07:00" /><i d="15.09.2016 19:02:06" n="internet.mts.ru" zp="" zv="" s="HSDPA (3G)" a="" du="222Kb" c="0" g="b" dup="300Kb" f="0" bd="15.09.2016 19:10:15" cur="810" gmt="+07:00" /><i d="15.09.2016 19:02:06" n="internet.mts.ru" zp="" zv="" s="HSDPA (3G)" a="" du="14Kb" c="0" g="e" dup="100Kb" f="0" bd="15.09.2016 19:10:33" cur="810" gmt="+07:00" /><i d="15.09.2016 20:04:16" n="79831245623" zp="" zv="" s="Телеф." a="" du="4:06" c="0" dup="5:00" f="0" bd="15.09.2016 20:08:22" cur="810" gmt="+07:00" /><i d="15.09.2016 20:39:39" n="internet.mts.ru" zp="" zv="" s="LTE (4G)" a="" du="104Kb" c="0" dup="200Kb" f="0" bd="15.09.2016 20:47:07" cur="810" gmt="+07:00" /><i d="15.09.2016 20:39:51" n="79139112855" zp="" zv="" s="Телеф." a="" du="10:00" c="0" dup="10:00" f="0" bd="15.09.2016 20:49:51" cur="810" gmt="+07:00" /><i d="16.09.2016 7:37:51" n="79139112855" zp="" zv="" s="Телеф." a="" du="0:07" c="0" dup="1:00" f="0" bd="16.09.2016 7:37:58" cur="810" gmt="+07:00" /><i d="16.09.2016 8:32:23" n="internet.mts.ru" zp="" zv="" s="LTE (4G)" a="" du="110Kb" c="0" dup="200Kb" f="0" bd="16.09.2016 8:38:58" cur="810" gmt="+07:00" /><i d="16.09.2016 10:10:42" n="internet.mts.ru" zp="" zv="" s="gprs" a="" du="236Kb" c="0" dup="300Kb" f="0" bd="16.09.2016 10:16:08" cur="810" gmt="+07:00" /><i d="16.09.2016 10:23:04" n="73832225550" zp="" zv="" s="Телеф." a="" du="0:15" c="1,2712" dup="1:00" f="1,5000" bd="16.09.2016 10:23:19" cur="810" gmt="+07:00" /><i d="16.09.2016 10:47:20" n="&lt;--79831245623" zp="" zv="" s="Телеф. (3G)" a="" du="0:18" c="0" dup="0:18" f="0" bd="16.09.2016 10:50:10" cur="810" gmt="+07:00" /><i d="16.09.2016 11:10:50" n="&lt;--sms:900" zp="" zv="" s="sms i" a="" du="0" c="0" dup="1" f="0" bd="16.09.2016 11:15:17" cur="810" gmt="+07:00" /><i d="16.09.2016 11:17:47" n="internet.mts.ru" zp="" zv="" s="LTE (4G)" a="" du="176Kb" c="0" dup="200Kb" f="0" bd="16.09.2016 11:25:08" cur="810" gmt="+07:00" /><i d="16.09.2016 11:42:14" n="79139112855" zp="" zv="" s="Телеф." a="" du="0:36" c="0" dup="1:00" f="0" bd="16.09.2016 11:42:50" cur="810" gmt="+07:00" /><i d="16.09.2016 12:03:03" n="79139247388" zp="" zv="" s="Телеф." a="" du="1:59" c="0" dup="2:00" f="0" bd="16.09.2016 12:05:02" cur="810" gmt="+07:00" /><i d="16.09.2016 12:23:26" n="internet.mts.ru" zp="" zv="" s="HSDPA (3G)" a="" du="83Kb" c="0" dup="100Kb" f="0" bd="16.09.2016 12:31:00" cur="810" gmt="+07:00" /><i d="16.09.2016 13:35:42" n="internet.mts.ru" zp="" zv="" s="HSDPA (3G)" a="" du="88Kb" c="0" dup="100Kb" f="0" bd="16.09.2016 13:43:11" cur="810" gmt="+07:00" /><i d="16.09.2016 14:55:58" n="internet.mts.ru" zp="" zv="" s="LTE (4G)" a="" du="53Kb" c="0" dup="100Kb" f="0" bd="16.09.2016 15:03:21" cur="810" gmt="+07:00" /><i d="16.09.2016 16:12:16" n="internet.mts.ru" zp="" zv="" s="LTE (4G)" a="" du="1737Kb" c="0" dup="1800Kb" f="0" bd="16.09.2016 16:20:09" cur="810" gmt="+07:00" /><i d="16.09.2016 16:48:07" n="&lt;--sms:NEPOSEDAcit" zp="" zv="" s="sms i" a="" du="0" c="0" dup="1" f="0" bd="16.09.2016 16:55:03" cur="810" gmt="+07:00" /><i d="16.09.2016 17:20:46" n="internet.mts.ru" zp="" zv="" s="LTE (4G)" a="" du="13Kb" c="0" dup="100Kb" f="0" bd="16.09.2016 17:28:06" cur="810" gmt="+07:00" /><i d="16.09.2016 18:07:21" n="&lt;--900" zp="" zv="" s="sms i" a="" du="1" c="0" g="b" dup="1" f="0" bd="16.09.2016 18:13:38" cur="810" gmt="+07:00" /><i d="16.09.2016 18:07:21" n="&lt;--900" zp="" zv="" s="sms i" a="" du="1" c="0" g="e" dup="1" f="0" bd="16.09.2016 18:13:38" cur="810" gmt="+07:00" /><i d="16.09.2016 18:07:34" n="internet.mts.ru" zp="" zv="" s="LTE (4G)" a="" du="18Kb" c="0" dup="100Kb" f="0" bd="16.09.2016 18:15:05" cur="810" gmt="+07:00" /><i d="16.09.2016 19:21:56" n="internet.mts.ru" zp="" zv="" s="HSDPA (3G)" a="" du="13764Kb" c="0" g="b" dup="13800Kb" f="0" bd="16.09.2016 19:29:14" cur="810" gmt="+07:00" /><i d="16.09.2016 19:21:57" n="internet.mts.ru" zp="" zv="" s="HSDPA (3G)" a="" du="15Kb" c="0" g="e" dup="100Kb" f="0" bd="16.09.2016 19:28:57" cur="810" gmt="+07:00" /><i d="16.09.2016 19:24:02" n="Traffic_Category_900_033.001_G" zp="" zv="" s="LTE (4G)" a="" du="1Kb" c="0" g="b" dup="1Kb" f="0" bd="16.09.2016 19:31:21" cur="810" gmt="+07:00" /><i d="16.09.2016 19:24:02" n="internet.mts.ru" zp="" zv="" s="gprs" a="" du="15Kb" c="0" g="e" dup="100Kb" f="0" bd="16.09.2016 19:31:22" cur="810" gmt="+07:00" /><i d="16.09.2016 19:49:23" n="79139112855" zp="" zv="" s="Телеф." a="" du="1:16" c="0" dup="2:00" f="0" bd="16.09.2016 19:50:39" cur="810" gmt="+07:00" /><i d="16.09.2016 20:58:18" n="internet.mts.ru" zp="" zv="" s="LTE (4G)" a="" du="160Kb" c="0" dup="200Kb" f="0" bd="16.09.2016 21:06:13" cur="810" gmt="+07:00" /><i d="16.09.2016 21:00:27" n="79831245623" zp="" zv="" s="Телеф." a="" du="10:39" c="0" dup="11:00" f="0" bd="16.09.2016 21:11:06" cur="810" gmt="+07:00" /><i d="16.09.2016 21:11:23" n="79139112855" zp="" zv="" s="Телеф." a="" du="5:42" c="0" dup="6:00" f="0" bd="16.09.2016 21:17:05" cur="810" gmt="+07:00" /><i d="17.09.2016 10:26:47" n="&lt;--79137031775" zp="" zv="" s="Телеф. (3G)" a="" du="0:23" c="0" dup="0:23" f="0" bd="17.09.2016 10:29:57" cur="810" gmt="+07:00" /><i d="17.09.2016 10:33:01" n="79139112855" zp="" zv="" s="Телеф." a="" du="0:35" c="0" dup="1:00" f="0" bd="17.09.2016 10:33:36" cur="810" gmt="+07:00" /><i d="17.09.2016 11:14:42" n="internet.mts.ru" zp="" zv="" s="LTE (4G)" a="" du="2107Kb" c="0" dup="2200Kb" f="0" bd="17.09.2016 11:23:13" cur="810" gmt="+07:00" /><i d="17.09.2016 11:20:07" n="&lt;--79139112855" zp="" zv="" s="Телеф. (3G)" a="" du="0:20" c="0" dup="0:20" f="0" bd="17.09.2016 11:24:56" cur="810" gmt="+07:00" /><i d="17.09.2016 11:32:31" n="internet.mts.ru" zp="" zv="" s="LTE (4G)" a="" du="5157Kb" c="0" dup="5200Kb" f="0" bd="17.09.2016 11:39:11" cur="810" gmt="+07:00" /><i d="17.09.2016 11:32:38" n="&lt;--79137031775" zp="" zv="" s="Телеф. (3G)" a="" du="0:13" c="0" dup="0:13" f="0" bd="17.09.2016 11:40:19" cur="810" gmt="+07:00" /><i d="17.09.2016 12:47:15" n="internet.mts.ru" zp="" zv="" s="HSDPA (3G)" a="" du="64Kb" c="0" dup="100Kb" f="0" bd="17.09.2016 12:56:14" cur="810" gmt="+07:00" /><i d="17.09.2016 13:56:20" n="internet.mts.ru" zp="" zv="" s="LTE (4G)" a="" du="2Kb" c="0" dup="100Kb" f="0" bd="17.09.2016 14:05:29" cur="810" gmt="+07:00" /><i d="17.09.2016 14:21:37" n="&lt;--79137031775" zp="" zv="" s="Телеф. (3G)" a="" du="0:30" c="0" dup="0:30" f="0" bd="17.09.2016 14:25:10" cur="810" gmt="+07:00" /><i d="17.09.2016 14:27:59" n="&lt;--79137031775" zp="" zv="" s="sms i" a="" du="1" c="0" dup="1" f="0" bd="17.09.2016 14:30:21" cur="810" gmt="+07:00" /><i d="17.09.2016 14:29:19" n="79137031775" zp="" zv="" s="sms o" a="" du="1" c="0" dup="1" f="0" bd="17.09.2016 14:29:20" cur="810" gmt="+07:00" /><i d="17.09.2016 14:56:34" n="internet.mts.ru" zp="" zv="" s="LTE (4G)" a="" du="76Kb" c="0" dup="100Kb" f="0" bd="17.09.2016 15:05:09" cur="810" gmt="+07:00" /><i d="17.09.2016 14:59:37" n="Traffic_Category_900_033.001_G" zp="" zv="" s="LTE (4G)" a="" du="1Kb" c="0" g="b" dup="1Kb" f="0" bd="17.09.2016 15:08:02" cur="810" gmt="+07:00" /><i d="17.09.2016 14:59:37" n="internet.mts.ru" zp="" zv="" s="HSDPA (3G)" a="" du="1Kb" c="0" g="e" dup="100Kb" f="0" bd="17.09.2016 15:07:54" cur="810" gmt="+07:00" /><i d="17.09.2016 15:51:08" n="79139247388" zp="" zv="" s="sms o" a="" du="1" c="0" dup="1" f="0" bd="17.09.2016 15:51:09" cur="810" gmt="+07:00" /><i d="17.09.2016 16:23:32" n="internet.mts.ru" zp="" zv="" s="LTE (4G)" a="" du="4Kb" c="0" dup="100Kb" f="0" bd="17.09.2016 16:32:02" cur="810" gmt="+07:00" /><i d="17.09.2016 18:12:49" n="internet.mts.ru" zp="" zv="" s="LTE (4G)" a="" du="47Kb" c="0" dup="100Kb" f="0" bd="17.09.2016 18:19:56" cur="810" gmt="+07:00" /><i d="17.09.2016 19:27:54" n="internet.mts.ru" zp="" zv="" s="LTE (4G)" a="" du="159Kb" c="0" dup="200Kb" f="0" bd="17.09.2016 19:35:16" cur="810" gmt="+07:00" /><i d="17.09.2016 19:35:35" n="&lt;--79139247388" zp="" zv="" s="sms i" a="" du="1" c="0" dup="1" f="0" bd="17.09.2016 19:41:39" cur="810" gmt="+07:00" /><i d="17.09.2016 20:48:19" n="internet.mts.ru" zp="" zv="" s="LTE (4G)" a="" du="94Kb" c="0" dup="100Kb" f="0" bd="17.09.2016 20:56:00" cur="810" gmt="+07:00" /></ds></Report>